{
    "name": null,
    "version": "1.0",
    "scrypt": {
        "n": 16384,
        "r": 8,
        "p": 8
    },
    "accounts": [
        {
            "address": "AKsh3x1XrpJAeERFRrR6kLvxpPed13cvKH",
            "label": null,
            "isDefault": false,
            "lock": false,
            "key": "6PYQ9UgdqztBLD6PU7X3XcKgLL4ogRihU6Jg98dZG49qxNM56h8VdBs3vR",
            "contract": {
                "script": "21024f3020e4ddc1603a81c89529f2fe9145bb37360b07082a6c62298acdf427fd38ac",
                "parameters": [
                    {
                        "name": "signature",
                        "type": "Signature"
                    }
                ],
                "deployed": false
            },
            "extra": null
        },
        {
            "address": "AZ8fAVAxvB7Gb8jMcGS2N21zAoiirGk5Ka",
            "label": null,
            "isDefault": false,
            "lock": false,
            "key": "6PYQ9UgdqztBLD6PU7X3XcKgLL4ogRihU6Jg98dZG49qxNM56h8VdBs3vR",
            "contract": {
                "script": "5121024f3020e4ddc1603a81c89529f2fe9145bb37360b07082a6c62298acdf427fd382102883118351f8f47107c83ab634dc7e4ffe29d274e7d3dcf70159c8935ff769beb52ae",
                "parameters": [
                    {
                        "name": "parameter0",
                        "type": "Signature"
                    }
                ],
                "deployed": false
            },
            "extra": null
        }
    ],
    "extra": null
}